game_utils/__init__.py
game_utils/controller.py
game_utils/demo.py
game_utils/game.py
game_utils/images.py
game_utils/physics.py
game_utils/screen.py
game_utils/sprites.py
game_utils/vector_utils.py
game_utils-1.1.3.dist-info/licenses/LICENSE
game_utils-1.1.3.dist-info/METADATA
game_utils-1.1.3.dist-info/WHEEL
game_utils-1.1.3.dist-info/top_level.txt
game_utils-1.1.3.dist-info/RECORD
