Metadata-Version: 2.4
Name: game-utils
Version: 1.1.3
Summary: A pygame engine for common game operations like vector math and maintaining events in the game loop
Author-email: Bee Hall <bhall1224@gmail.com>
Project-URL: Homepage, https://github.com/bhall1224/game-utils
Classifier: Programming Language :: Python :: 3
Classifier: License :: OSI Approved :: MIT License
Classifier: Operating System :: OS Independent
Requires-Python: >=3.11
License-File: LICENSE
Requires-Dist: pygame
Requires-Dist: numpy
Dynamic: license-file
